hello.py
utils/__init__.py
utils/messages.py
cli_msg-4.1.0.dist-info/LICENSE
cli_msg-4.1.0.dist-info/METADATA
cli_msg-4.1.0.dist-info/WHEEL
cli_msg-4.1.0.dist-info/entry_points.txt
cli_msg-4.1.0.dist-info/top_level.txt
cli_msg-4.1.0.dist-info/RECORD
